bergen/__init__.py
bergen/actors/__init__.py
bergen/actors/base.py
bergen/actors/classic.py
bergen/actors/functional.py
bergen/actors/utils.py
bergen/auths/__init__.py
bergen/auths/backend/__init__.py
bergen/auths/backend/app.py
bergen/auths/base.py
bergen/auths/code/__init__.py
bergen/auths/code/app.py
bergen/auths/code/widgets/login.py
bergen/auths/implicit/__init__.py
bergen/auths/implicit/app.py
bergen/auths/implicit/widgets/login.py
bergen/auths/legacy/__init__.py
bergen/auths/legacy/app.py
bergen/auths/messages/__init__.py
bergen/auths/messages/base.py
bergen/auths/messages/exception.py
bergen/auths/messages/generics.py
bergen/auths/messages/postman/__init__.py
bergen/auths/messages/postman/assign/__init__.py
bergen/auths/messages/postman/assign/assign.py
bergen/auths/messages/postman/assign/assign_cancelled.py
bergen/auths/messages/postman/assign/assign_critical.py
bergen/auths/messages/postman/assign/assign_done.py
bergen/auths/messages/postman/assign/assign_log.py
bergen/auths/messages/postman/assign/assign_return.py
bergen/auths/messages/postman/assign/assign_yield.py
bergen/auths/messages/postman/assign/bounced_assign.py
bergen/auths/messages/postman/assign/bounced_forwarded_assign.py
bergen/auths/messages/postman/exception.py
bergen/auths/messages/postman/log.py
bergen/auths/messages/postman/provide/__init__.py
bergen/auths/messages/postman/provide/bounced_provide.py
bergen/auths/messages/postman/provide/params.py
bergen/auths/messages/postman/provide/provide.py
bergen/auths/messages/postman/provide/provide_critical.py
bergen/auths/messages/postman/provide/provide_done.py
bergen/auths/messages/postman/provide/provide_log.py
bergen/auths/messages/postman/provide/provide_transition.py
bergen/auths/messages/postman/reserve/__init__.py
bergen/auths/messages/postman/reserve/bounced_forwarded_reserve.py
bergen/auths/messages/postman/reserve/bounced_reserve.py
bergen/auths/messages/postman/reserve/params.py
bergen/auths/messages/postman/reserve/reserve.py
bergen-0.4.75.dist-info/WHEEL
bergen-0.4.75.dist-info/METADATA
bergen-0.4.75.dist-info/RECORD
