Metadata-Version: 2.1
Name: bergen
Version: 0.4.75
Summary: A python client for the Arnheim Framework
Home-page: https://github.com/jhnnsrs/bergen
License: CC BY-NC 3.0
Author: jhnnsrs
Author-email: jhnnsrs@gmail.com
Requires-Python: >=3.6.1,<3.10
Classifier: License :: Other/Proprietary License
Classifier: Programming Language :: Python :: 3
Classifier: Programming Language :: Python :: 3.7
Classifier: Programming Language :: Python :: 3.8
Classifier: Programming Language :: Python :: 3.9
Provides-Extra: gql
Provides-Extra: pyqt
Provides-Extra: pyside
Requires-Dist: PyQt5 (>=5.15.4,<6.0.0); extra == "pyqt"
Requires-Dist: PyQtWebEngine (>=5.15.4,<6.0.0); extra == "pyqt" or extra == "pyside"
Requires-Dist: PySide2 (>=5.15.2,<6.0.0); extra == "pyside"
Requires-Dist: PyYAML (>=5.4.1,<6.0.0)
Requires-Dist: aiohttp (>=3.7.4,<4.0.0)
Requires-Dist: aiostream (>=0.4.1,<0.5.0)
Requires-Dist: contextvars (>=2.2,<3.0); python_version >= "3.6" and python_version < "3.8"
Requires-Dist: docstring-parser (>=0.7.3,<0.8.0)
Requires-Dist: gql[all] (>=3.0.0a5,<4.0.0); extra == "gql"
Requires-Dist: janus (>=0.6.1,<0.7.0)
Requires-Dist: namegenerator (>=1.0.6,<2.0.0)
Requires-Dist: nest-asyncio (>=1.5.1,<2.0.0)
Requires-Dist: pydantic (>=1.7.3,<2.0.0)
Requires-Dist: requests (>=2.25.1,<3.0.0)
Requires-Dist: requests-oauthlib (>=1.3.0,<2.0.0)
Requires-Dist: rich (>=10.1.0,<11.0.0)
Requires-Dist: tqdm (>=4.56.1,<5.0.0)
Requires-Dist: websockets (>=8.1,<9.0)
